te3/__init__.py
te3/aa.py
te3/data/embeddings.csv
te3-0.0.1.dist-info/METADATA
te3-0.0.1.dist-info/WHEEL
te3-0.0.1.dist-info/top_level.txt
te3-0.0.1.dist-info/RECORD
