Metadata-Version: 2.1
Name: te3
Version: 0.0.1
Summary: test_func
Home-page: https://github.com/dreji18/environmental-due-diligence
Author: Afreen Aman, Deepak John Reji
Author-email: afreenaman90@gmail.com
License: MIT
Classifier: License :: OSI Approved :: MIT License
Classifier: Programming Language :: Python :: 3.6
Classifier: Programming Language :: Python :: 3.7
Classifier: Programming Language :: Python :: 3.8
Requires-Dist: numpy
Requires-Dist: pandas
